yfrlt/__init__.py
yfrlt/client.py
yfrlt/exceptions.py
yfrlt/models.py
yfrlt/parser.py
yfrlt-1.0.0.dist-info/licenses/LICENSE
yfrlt-1.0.0.dist-info/METADATA
yfrlt-1.0.0.dist-info/WHEEL
yfrlt-1.0.0.dist-info/top_level.txt
yfrlt-1.0.0.dist-info/RECORD
