Metadata-Version: 2.4
Name: yfrlt
Version: 1.0.0
Summary: Yahoo Finance Real-Time WebSocket Library for streaming live market data
Home-page: https://github.com/ijuice-20/yfrlt
Author: ijuice-20
Author-email: YFRLT Community <support@yfrlt.dev>
License: MIT
Project-URL: Homepage, https://github.com/ijuice-20/yfrlt
Project-URL: Repository, https://github.com/ijuice-20/yfrlt
Project-URL: Issues, https://github.com/ijuice-20/yfrlt/issues
Project-URL: Documentation, https://github.com/ijuice-20/yfrlt#readme
Keywords: yahoo,finance,websocket,realtime,stocks,crypto,trading,market-data,financial-data,streaming
Classifier: Development Status :: 4 - Beta
Classifier: Intended Audience :: Developers
Classifier: Intended Audience :: Financial and Insurance Industry
Classifier: License :: OSI Approved :: MIT License
Classifier: Operating System :: OS Independent
Classifier: Programming Language :: Python :: 3
Classifier: Programming Language :: Python :: 3.8
Classifier: Programming Language :: Python :: 3.9
Classifier: Programming Language :: Python :: 3.10
Classifier: Programming Language :: Python :: 3.11
Classifier: Programming Language :: Python :: 3.12
Classifier: Topic :: Office/Business :: Financial
Classifier: Topic :: Software Development :: Libraries :: Python Modules
Requires-Python: >=3.8
License-File: LICENSE
Requires-Dist: websocket-client>=1.6.0
Requires-Dist: websockets>=11.0.0
Dynamic: author
Dynamic: home-page
Dynamic: license-file
Dynamic: requires-python
